{
  "name": "forzani-tickets",
  "version": "1.0.0",
  "description": "Sistema de gestión de tickets (Help Desk) con monorepo Turborepo",
  "private": true,
  "workspaces": [
    "apps/*",
    "packages/*"
  ],
  "scripts": {
    "dev": "turbo run dev --parallel",
    "build": "turbo run build",
    "lint": "turbo run lint",
    "test": "turbo run test",
    "seed": "turbo run seed",
    "db:migrate": "turbo run db:migrate",
    "db:generate": "turbo run db:generate",
    "packages:build": "pnpm --filter @forzani/types build && pnpm --filter @forzani/ui build",
    "setup:db": "pnpm --filter @forzani/api db:generate && pnpm --filter @forzani/api db:migrate && pnpm --filter @forzani/api db:seed",
    "dev:api": "pnpm --filter @forzani/api dev",
    "dev:web": "pnpm --filter @forzani/web dev",
    "stack:up": "cd infra/docker && docker compose up -d",
    "stack:down": "cd infra/docker && docker compose down",
    "stack:rebuild": "cd infra/docker && docker compose up -d --build",
    "clean": "turbo run clean",
    "format": "prettier --write \"**/*.{ts,tsx,js,jsx,json,md}\""
  },
  "devDependencies": {
    "@turbo/gen": "^1.12.4",
    "prettier": "^3.1.1",
    "turbo": "^1.12.4",
    "typescript": "^5.3.3"
  },
  "packageManager": "pnpm@8.15.0",
  "engines": {
    "node": ">=18.0.0",
    "pnpm": ">=8.0.0"
  }
}
